tinygs_qos/__init__.py
tinygs_qos/predictor.py
tinygs_qos/utils/__init__.py
tinygs_qos/utils/tiny_utils.py
tinygs_qos-0.1.0.dist-info/METADATA
tinygs_qos-0.1.0.dist-info/WHEEL
tinygs_qos-0.1.0.dist-info/RECORD
