Metadata-Version: 2.3
Name: tinygs-qos
Version: 0.1.0
Summary: Predict TinyGS network coverage for different LoRa configurations
License: MIT
Author: coleandreoli
Author-email: coleandreoli@gmail.com
Requires-Python: >=3.12
Classifier: License :: OSI Approved :: MIT License
Classifier: Programming Language :: Python :: 3
Classifier: Programming Language :: Python :: 3.12
Classifier: Programming Language :: Python :: 3.13
Requires-Dist: matplotlib (>=3.9.0,<3.10.0)
Requires-Dist: numpy (>=1.26.4,<2.0.0)
Requires-Dist: pandas (>=2.3.3,<3.0.0)
Requires-Dist: pulearn (>=0.0.11,<0.0.12)
Requires-Dist: pymap3d (>=3.2.0,<4.0.0)
Requires-Dist: scikit-learn (==1.5.2)
Requires-Dist: scipy (>=1.17.0,<2.0.0)
Requires-Dist: streamlit (>=1.53.0,<2.0.0)
